odoo8_addon_base_geoengine_demo-8.0.0.1.0.99.dev22-py2.7-nspkg.pth
odoo8_addon_base_geoengine_demo-8.0.0.1.0.99.dev22.dist-info/DESCRIPTION.rst
odoo8_addon_base_geoengine_demo-8.0.0.1.0.99.dev22.dist-info/METADATA
odoo8_addon_base_geoengine_demo-8.0.0.1.0.99.dev22.dist-info/RECORD
odoo8_addon_base_geoengine_demo-8.0.0.1.0.99.dev22.dist-info/WHEEL
odoo8_addon_base_geoengine_demo-8.0.0.1.0.99.dev22.dist-info/metadata.json
odoo8_addon_base_geoengine_demo-8.0.0.1.0.99.dev22.dist-info/namespace_packages.txt
odoo8_addon_base_geoengine_demo-8.0.0.1.0.99.dev22.dist-info/top_level.txt
odoo_addons/base_geoengine_demo/README.rst
odoo_addons/base_geoengine_demo/__init__.py
odoo_addons/base_geoengine_demo/__openerp__.py
odoo_addons/base_geoengine_demo/geo_npa.py
odoo_addons/base_geoengine_demo/retail_machine.py
odoo_addons/base_geoengine_demo/retail_machine_view.xml
odoo_addons/base_geoengine_demo/zip_view.xml
odoo_addons/base_geoengine_demo/data/npa_geom.xml
odoo_addons/base_geoengine_demo/data/retail_machine_geom.xml
odoo_addons/base_geoengine_demo/i18n/am.po
odoo_addons/base_geoengine_demo/i18n/ar.po
odoo_addons/base_geoengine_demo/i18n/bg.po
odoo_addons/base_geoengine_demo/i18n/bs.po
odoo_addons/base_geoengine_demo/i18n/ca.po
odoo_addons/base_geoengine_demo/i18n/cs.po
odoo_addons/base_geoengine_demo/i18n/da.po
odoo_addons/base_geoengine_demo/i18n/de.po
odoo_addons/base_geoengine_demo/i18n/el_GR.po
odoo_addons/base_geoengine_demo/i18n/en_GB.po
odoo_addons/base_geoengine_demo/i18n/es.po
odoo_addons/base_geoengine_demo/i18n/es_AR.po
odoo_addons/base_geoengine_demo/i18n/es_CL.po
odoo_addons/base_geoengine_demo/i18n/es_CO.po
odoo_addons/base_geoengine_demo/i18n/es_CR.po
odoo_addons/base_geoengine_demo/i18n/es_DO.po
odoo_addons/base_geoengine_demo/i18n/es_EC.po
odoo_addons/base_geoengine_demo/i18n/es_ES.po
odoo_addons/base_geoengine_demo/i18n/es_MX.po
odoo_addons/base_geoengine_demo/i18n/es_PE.po
odoo_addons/base_geoengine_demo/i18n/es_PY.po
odoo_addons/base_geoengine_demo/i18n/es_VE.po
odoo_addons/base_geoengine_demo/i18n/et.po
odoo_addons/base_geoengine_demo/i18n/eu.po
odoo_addons/base_geoengine_demo/i18n/fa.po
odoo_addons/base_geoengine_demo/i18n/fi.po
odoo_addons/base_geoengine_demo/i18n/fr.po
odoo_addons/base_geoengine_demo/i18n/fr_CA.po
odoo_addons/base_geoengine_demo/i18n/fr_CH.po
odoo_addons/base_geoengine_demo/i18n/gl.po
odoo_addons/base_geoengine_demo/i18n/gl_ES.po
odoo_addons/base_geoengine_demo/i18n/he.po
